odoo10_addon_web_decimal_numpad_dot-10.0.1.1.0-py2.7-nspkg.pth
odoo/addons/web_decimal_numpad_dot/README.rst
odoo/addons/web_decimal_numpad_dot/__init__.py
odoo/addons/web_decimal_numpad_dot/__manifest__.py
odoo/addons/web_decimal_numpad_dot/static/description/icon.png
odoo/addons/web_decimal_numpad_dot/static/src/js/numpad_dot.js
odoo/addons/web_decimal_numpad_dot/views/web_decimal_numpad_dot.xml
odoo10_addon_web_decimal_numpad_dot-10.0.1.1.0.dist-info/DESCRIPTION.rst
odoo10_addon_web_decimal_numpad_dot-10.0.1.1.0.dist-info/METADATA
odoo10_addon_web_decimal_numpad_dot-10.0.1.1.0.dist-info/RECORD
odoo10_addon_web_decimal_numpad_dot-10.0.1.1.0.dist-info/WHEEL
odoo10_addon_web_decimal_numpad_dot-10.0.1.1.0.dist-info/metadata.json
odoo10_addon_web_decimal_numpad_dot-10.0.1.1.0.dist-info/namespace_packages.txt
odoo10_addon_web_decimal_numpad_dot-10.0.1.1.0.dist-info/top_level.txt
