Metadata-Version: 2.0
Name: odoo10-addon-web-decimal-numpad-dot
Version: 10.0.1.1.0
Summary: Allows using numpad dot to enter period decimal separator
Home-page: https://odoo-community.org/
Author: AvanzOSC, Comunitea, Tecnativa, Odoo Community Association (OCA)
Author-email: support@odoo-community.org
License: AGPL-3
Platform: UNKNOWN
Classifier: Programming Language :: Python :: 2.7
Classifier: Framework :: Odoo
Classifier: License :: OSI Approved :: GNU Affero General Public License v3
Requires-Dist: odoo (<10.1dev,>=10.0)
